agentic_kit_common/__init__.py
agentic_kit_common/config/__init__.py
agentic_kit_common/config/config_loader.py
agentic_kit_common/llm/__init__.py
agentic_kit_common/llm/llm.py
agentic_kit_common/llm/openai.py
agentic_kit_common/llm/utils.py
agentic_kit_common/log/__init__.py
agentic_kit_common/log/logger.py
agentic_kit_common/mcp/__init__.py
agentic_kit_common/mcp/mcp_client.py
agentic_kit_common/minio/__init__.py
agentic_kit_common/minio/minio_manager.py
agentic_kit_common/mongodb/__init__.py
agentic_kit_common/mongodb/mongodb_manager.py
agentic_kit_common/orm/__init__.py
agentic_kit_common/orm/base.py
agentic_kit_common/orm/execution.py
agentic_kit_common/orm/manager.py
agentic_kit_common/orm/multi_session.py
agentic_kit_common/orm/schema.py
agentic_kit_common/orm/session.py
agentic_kit_common/redis/__init__.py
agentic_kit_common/redis/redis_pool_manager.py
agentic_kit_common/sms/__init__.py
agentic_kit_common/sms/ali_sms_client.py
agentic_kit_common/tool_call/__init__.py
agentic_kit_common/tool_call/tool_call.py
agentic_kit_common/vector/__init__.py
agentic_kit_common/vector/embedding/__init__.py
agentic_kit_common/vector/embedding/embedding.py
agentic_kit_common/vector/manager/__init__.py
agentic_kit_common/vector/manager/milvus_manager.py
agentic_kit_common/vector/schema/__init__.py
agentic_kit_common/vector/schema/base.py
agentic_kit_common/vector/schema/milvus_schema.py
agentic_kit_common/web/__init__.py
agentic_kit_common/web/http/__init__.py
agentic_kit_common/web/http/response.py
test/__init__.py
test/conf.yaml
test/config.py
test/settings.py
test/test_config_manager.py
test/test_embedding.py
test/test_mcp_client.py
test/test_minio.py
test/test_orm.py
test/test_redis_pool_manager.py
test/test_vector.py
agentic_kit_common-0.0.25.dist-info/METADATA
agentic_kit_common-0.0.25.dist-info/WHEEL
agentic_kit_common-0.0.25.dist-info/top_level.txt
agentic_kit_common-0.0.25.dist-info/RECORD
