Metadata-Version: 2.4
Name: agentic-kit-common
Version: 0.0.25
Summary: Common utilities and tools for agentic kit ecosystem
Home-page: 
Author: manson
Author-email: manson.li3307@gmail.com
Keywords: AI,LLM,Agent,MinIO,Storage,Common,Utilities
Classifier: Development Status :: 4 - Beta
Classifier: Intended Audience :: Developers
Classifier: Topic :: Scientific/Engineering :: Artificial Intelligence
Classifier: Topic :: Software Development :: Libraries :: Python Modules
Classifier: Topic :: System :: Distributed Computing
Classifier: Programming Language :: Python :: 3
Classifier: License :: OSI Approved :: Apache Software License
Classifier: Operating System :: OS Independent
Requires-Python: >=3.12
Requires-Dist: minio
Requires-Dist: urllib3
Requires-Dist: pydantic
Requires-Dist: requests
Requires-Dist: langchain_core
Requires-Dist: langgraph
Requires-Dist: langchain_community
Requires-Dist: langchain_experimental
Requires-Dist: langchain-openai
Requires-Dist: langchain_mcp_adapters
Requires-Dist: mysql-connector-python
Requires-Dist: sqlalchemy
Requires-Dist: sqlglot
Requires-Dist: pymilvus
Requires-Dist: xinference_client
Requires-Dist: pymongo
Requires-Dist: redis
Requires-Dist: aliyun-python-sdk-core
Requires-Dist: aliyun-python-sdk-dysmsapi
Dynamic: author
Dynamic: author-email
Dynamic: classifier
Dynamic: description
Dynamic: description-content-type
Dynamic: keywords
Dynamic: requires-dist
Dynamic: requires-python
Dynamic: summary
